dig_ass_text_protos/DigitalAssistantText_pb2.py
dig_ass_text_protos/DigitalAssistantText_pb2.pyi
dig_ass_text_protos/DigitalAssistantText_pb2_grpc.py
dig_ass_text_protos/__init__.py
dig_ass_text_protos/client.py
dig_ass_text_protos-3.3.1.dist-info/METADATA
dig_ass_text_protos-3.3.1.dist-info/WHEEL
dig_ass_text_protos-3.3.1.dist-info/top_level.txt
dig_ass_text_protos-3.3.1.dist-info/RECORD
