Metadata-Version: 2.4
Name: dig_ass_text_protos
Version: 3.3.1
Summary: Proto files for dig_ass_text_protos
Author: AGI-MED-TEAM
Requires-Python: >=3.11
Requires-Dist: agi-med-protos==2.2.0
